access/__init__.py
access/access.py
access/datasets.py
access/fca.py
access/helpers.py
access/raam.py
access/weights.py
access/tests/test_access.py
access/tests/test_datasets.py
access/tests/test_euclidean.py
access/tests/test_floating_catchment_area.py
access/tests/test_helpers.py
access/tests/test_hospital_example.py
access/tests/test_misc.py
access/tests/test_raam.py
access/tests/test_weighted_catchment.py
access/tests/test_weights.py
access/tests/util.py
access/tests/data/model_output.json
access-1.1.10.post3.dist-info/licenses/LICENSE
access-1.1.10.post3.dist-info/METADATA
access-1.1.10.post3.dist-info/WHEEL
access-1.1.10.post3.dist-info/top_level.txt
access-1.1.10.post3.dist-info/RECORD
